crossense/__init__.py
crossense/ensemble/__init__.py
crossense/ensemble/_bagging.py
crossense/ensemble/tests/__init__.py
crossense/ensemble/tests/test_bagging.py
crossense-0.1.0.dist-info/METADATA
crossense-0.1.0.dist-info/WHEEL
crossense-0.1.0.dist-info/RECORD
