Metadata-Version: 2.1
Name: crossense
Version: 0.1.0
Summary: some helpers to train or inference scikit-learn models
Home-page: https://github.com/Zeeonome/crossense
License: MIT
Author: zeenome longevity
Author-email: dev@zeenome.com
Requires-Python: >=3.10,<4.0
Classifier: License :: OSI Approved :: MIT License
Classifier: Programming Language :: Python :: 3
Classifier: Programming Language :: Python :: 3.10
Classifier: Programming Language :: Python :: 3.11
Classifier: Programming Language :: Python :: 3.12
Requires-Dist: scikit-learn (>=1.3.2,<2.0.0)
Project-URL: Repository, https://github.com/Zeeonome/crossense
